FC_Cedibles_SDK-1.0.1.4.dist-info/METADATA
FC_Cedibles_SDK-1.0.1.4.dist-info/RECORD
FC_Cedibles_SDK-1.0.1.4.dist-info/WHEEL
FC_Cedibles_SDK-1.0.1.4.dist-info/top_level.txt
fc/__init__.py
fc/cediblessdk/__init__.py
fc/cediblessdk/classes/__init__.py
fc/cediblessdk/classes/documentoCedible.py
fc/cediblessdk/classes/documentoCedibleSubs.py
fc/cediblessdk/classes/utils.py
fc/cediblessdk/schemas/DocumentoCedible_v10.xsd
fc/cediblessdk/schemas/SiiTypes_v10.xsd
fc/cediblessdk/schemas/xmldsignature_v10.xsd
