Metadata-Version: 2.1
Name: FC-Cedibles-SDK
Version: 1.0.1.4
Summary: SDK for Cedibles documents
Home-page: https://bitbucket.org/elasbit/fc-cedibledocs-lib
Author: Jose Fidalgo H.
Author-email: jfidalgo@factorclick.com
License: UNKNOWN
Platform: UNKNOWN
Classifier: Programming Language :: Python :: 2
Classifier: Operating System :: OS Independent
